aws_spy/__init__.py
aws_spy/dependencies.py
aws_spy/main.py
aws_spy/responses.py
aws_spy/test.py
aws_spy/core/__init__.py
aws_spy/core/encoders.py
aws_spy/core/event_utils.py
aws_spy/core/exceptions.py
aws_spy/core/logging.py
aws_spy/core/params.py
aws_spy/core/params_alias.py
aws_spy/core/responses.py
aws_spy/core/schemas.py
aws_spy/core/schemas_utils.py
aws_spy/core/types.py
aws_spy/helpers/__init__.py
aws_spy/helpers/cli.py
aws_spy/helpers/documentation.py
aws_spy/helpers/exceptions.py
aws_spy/helpers/utils.py
aws_spy/layer/spy-layer.yml
aws_spy/layer/spy/python/annotated_types/__init__.py
aws_spy/layer/spy/python/annotated_types/py.typed
aws_spy/layer/spy/python/pydantic_core/__init__.py
aws_spy/layer/spy/python/pydantic_core/_pydantic_core.cpython-310-aarch64-linux-gnu.so
aws_spy/layer/spy/python/pydantic_core/_pydantic_core.pyi
aws_spy/layer/spy/python/pydantic_core/core_schema.py
aws_spy/layer/spy/python/pydantic_core/py.typed
aws_spy-0.2.11.dist-info/METADATA
aws_spy-0.2.11.dist-info/WHEEL
aws_spy-0.2.11.dist-info/entry_points.txt
aws_spy-0.2.11.dist-info/licenses/LICENSE
aws_spy-0.2.11.dist-info/RECORD
