Metadata-Version: 2.1
Name: aws-spy
Version: 0.2.11
Project-URL: Homepage, https://github.com/PiochU19/aws-spy
Project-URL: Documentation, https://github.com/PiochU19/aws-spy#readme
Project-URL: Issues, https://github.com/PiochU19/aws-spy/issues
Project-URL: Source, https://github.com/PiochU19/aws-spy
Author-email: Dominik Pioś <792954018@wp.pl>
License: The MIT License (MIT)
License-File: LICENSE
Classifier: Development Status :: 4 - Beta
Classifier: License :: OSI Approved :: MIT License
Classifier: Programming Language :: Python
Classifier: Programming Language :: Python :: 3.10
Classifier: Programming Language :: Python :: Implementation :: CPython
Classifier: Programming Language :: Python :: Implementation :: PyPy
Requires-Python: <3.11.0,>=3.10.0
Requires-Dist: pydantic>=2.0.0
Requires-Dist: pyyaml>=6.0
